twitter_fire_scraper_webapi/__init__.py
twitter_fire_scraper_webapi/app.py
twitter_fire_scraper_webapi/tests/__init__.py
twitter_fire_scraper_webapi/tests/test/__init__.py
twitter_fire_scraper_webapi/tests/test/__main__.py
twitter_fire_scraper_webapi-0.0.1.dist-info/METADATA
twitter_fire_scraper_webapi-0.0.1.dist-info/WHEEL
twitter_fire_scraper_webapi-0.0.1.dist-info/top_level.txt
twitter_fire_scraper_webapi-0.0.1.dist-info/RECORD
